kurumii_events/__init__.py
kurumii_events/events/__init__.py
kurumii_events/events/event_manager.py
kurumii_events/events/exceptions.py
kurumii_events/events/singleton/__init__.py
kurumii_events/events/singleton/event_manager.py
kurumii_events-0.0.3.8.dist-info/METADATA
kurumii_events-0.0.3.8.dist-info/WHEEL
kurumii_events-0.0.3.8.dist-info/entry_points.txt
kurumii_events-0.0.3.8.dist-info/top_level.txt
kurumii_events-0.0.3.8.dist-info/RECORD
