Metadata-Version: 2.1
Name: kurumii_events
Version: 0.0.3.8
Summary: A Module containing a basic Event System
Classifier: Programming Language :: Python :: 3
Classifier: License :: OSI Approved :: MIT License
Classifier: Operating System :: OS Independent
Requires-Python: >=3.7
